dockdj/__init__.py
dockdj/__main__.py
dockdj/deploy.py
dockdj/docker.txt
dockdj/du_settings.py
dockdj/init.py
dockdj/nginx.jinja
dockdj/nginx_docker.txt
dockdj/setup.py
dockdj/util.py
dockdj-2.2.2.dist-info/METADATA
dockdj-2.2.2.dist-info/WHEEL
dockdj-2.2.2.dist-info/entry_points.txt
dockdj-2.2.2.dist-info/top_level.txt
dockdj-2.2.2.dist-info/RECORD
