Metadata-Version: 2.1
Name: dockdj
Version: 2.2.2
Summary: Deploy the Django app to Ubuntu server as docker container.
Home-page: https://github.com/pavanputhra/dockdj
Author: Pavan Kumar
Author-email: pavanputhra@gmail.com
License: MIT
Platform: UNKNOWN
Classifier: License :: OSI Approved :: MIT License
Classifier: Programming Language :: Python :: 3
Classifier: Programming Language :: Python :: 3.7
Requires-Dist: fabric
Requires-Dist: PyYAML
